{"a89e6884d5546e1fd1042cb2":{"word_id":"a89e6884d5546e1fd1042cb2","display_form":"最も","lemma_form":"最も","reading":"もっとも","pos_major":"副詞","pos_label":"副词","pos_bucket":"adverb","group":"content","group_label":"实词","counts":{"all":189,"total":189,"solving":188,"listening_prompt":0,"listening_transcript":1,"listening_asr":0,"listening_heard":1,"listening_total":1},"paper_counts":{"all":29,"solving":29,"listening_prompt":0,"listening_heard":1,"listening_total":1},"first_year":1998,"last_year":2025,"years_present":["1998","1999","2000","2001","2002","2003","2004","2005","2006","2007","2008","2009","2010","2011","2012","2013","2014","2015","2016","2017","2018","2019","2020","2021","2022","2023","2024","2025"],"source_flags":["solving","listening_transcript"],"has_asr":false,"quality_flags":[],"dict_query":"最も","dict_query_alt":["もっとも"],"moji_url":"https://www.mojidict.com/searchText/%E6%9C%80%E3%82%82","surface_variant_count":2,"reading_variant_count":1,"sense_ambiguous":false,"variants_preview":[["最も",183],["もっとも",6]],"top_sources":[{"paper_id":"gaokao-ja-2015-national-standard","paper_label":"2015 全国卷","year":"2015","solving":18,"listening_prompt":0,"listening_transcript":0,"listening_asr":0,"total":18,"has_asr":false,"quality_flags":[],"source_label":"解题","source_breakdown":"解题18 / 合计18"},{"paper_id":"gaokao-ja-2009-national-standard","paper_label":"2009 全国卷","year":"2009","solving":13,"listening_prompt":0,"listening_transcript":0,"listening_asr":0,"total":13,"has_asr":false,"quality_flags":[],"source_label":"解题","source_breakdown":"解题13 / 合计13"},{"paper_id":"gaokao-ja-2000-national-standard","paper_label":"2000 全国卷","year":"2000","solving":10,"listening_prompt":0,"listening_transcript":0,"listening_asr":0,"total":10,"has_asr":false,"quality_flags":[],"source_label":"解题","source_breakdown":"解题10 / 合计10"}],"dictionary":{"source":"JMdict","headword":"最も","reading":"もっとも","glosses":["most","extremely"],"parts":["adv"],"entry_id":"1293700"},"examples":[{"text":"文中の(1)に入れるのに最も適当なものはどれか。","paper_label":"1998 全国卷","paper_id":"gaokao-ja-1998-national-standard","year":"1998","source":"解题","has_asr":false},{"text":"文中の(2)に入れるのに最も適当なものはどれか。","paper_label":"1998 全国卷","paper_id":"gaokao-ja-1998-national-standard","year":"1998","source":"解题","has_asr":false},{"text":"文中の(3)に入れるのに最も適当なものはどれか。","paper_label":"1998 全国卷","paper_id":"gaokao-ja-1998-national-standard","year":"1998","source":"解题","has_asr":false},{"text":"文中の(4)に入れるのに最も適当なものはどれか。","paper_label":"1998 全国卷","paper_id":"gaokao-ja-1998-national-standard","year":"1998","source":"解题","has_asr":false},{"text":"文中の(ア)に入れるのに最も適当なものはどれか。","paper_label":"1999 全国卷","paper_id":"gaokao-ja-1999-national-standard","year":"1999","source":"解题","has_asr":false},{"text":"文中の(イ)に入れるのに最も適当なものはどれか。","paper_label":"1999 全国卷","paper_id":"gaokao-ja-1999-national-standard","year":"1999","source":"解题","has_asr":false}],"variant_counts":[["最も",183],["もっとも",6]],"year_distribution":{"1998":4,"1999":7,"2000":10,"2001":5,"2002":7,"2003":7,"2004":8,"2005":5,"2006":3,"2007":7,"2008":6,"2009":13,"2010":5,"2011":9,"2012":4,"2013":5,"2014":8,"2015":18,"2016":5,"2017":6,"2018":6,"2019":5,"2020":7,"2021":4,"2022":7,"2023":6,"2024":10,"2025":2},"paper_distribution":[{"paper_id":"gaokao-ja-2015-national-standard","paper_label":"2015 全国卷","year":"2015","solving":18,"listening_prompt":0,"listening_transcript":0,"listening_asr":0,"total":18,"has_asr":false,"quality_flags":[],"source_label":"解题","source_breakdown":"解题18 / 合计18"},{"paper_id":"gaokao-ja-2009-national-standard","paper_label":"2009 全国卷","year":"2009","solving":13,"listening_prompt":0,"listening_transcript":0,"listening_asr":0,"total":13,"has_asr":false,"quality_flags":[],"source_label":"解题","source_breakdown":"解题13 / 合计13"},{"paper_id":"gaokao-ja-2000-national-standard","paper_label":"2000 全国卷","year":"2000","solving":10,"listening_prompt":0,"listening_transcript":0,"listening_asr":0,"total":10,"has_asr":false,"quality_flags":[],"source_label":"解题","source_breakdown":"解题10 / 合计10"},{"paper_id":"gaokao-ja-2011-national-standard","paper_label":"2011 全国卷","year":"2011","solving":9,"listening_prompt":0,"listening_transcript":0,"listening_asr":0,"total":9,"has_asr":false,"quality_flags":[],"source_label":"解题","source_breakdown":"解题9 / 合计9"},{"paper_id":"gaokao-ja-2004-national-standard","paper_label":"2004 全国卷","year":"2004","solving":8,"listening_prompt":0,"listening_transcript":0,"listening_asr":0,"total":8,"has_asr":false,"quality_flags":[],"source_label":"解题","source_breakdown":"解题8 / 合计8"},{"paper_id":"gaokao-ja-2014-national-standard","paper_label":"2014 全国卷","year":"2014","solving":8,"listening_prompt":0,"listening_transcript":0,"listening_asr":0,"total":8,"has_asr":false,"quality_flags":[],"source_label":"解题","source_breakdown":"解题8 / 合计8"},{"paper_id":"gaokao-ja-1999-national-standard","paper_label":"1999 全国卷","year":"1999","solving":7,"listening_prompt":0,"listening_transcript":0,"listening_asr":0,"total":7,"has_asr":false,"quality_flags":[],"source_label":"解题","source_breakdown":"解题7 / 合计7"},{"paper_id":"gaokao-ja-2002-national-standard","paper_label":"2002 全国卷","year":"2002","solving":7,"listening_prompt":0,"listening_transcript":0,"listening_asr":0,"total":7,"has_asr":false,"quality_flags":[],"source_label":"解题","source_breakdown":"解题7 / 合计7"},{"paper_id":"gaokao-ja-2003-national-standard","paper_label":"2003 全国卷","year":"2003","solving":7,"listening_prompt":0,"listening_transcript":0,"listening_asr":0,"total":7,"has_asr":false,"quality_flags":[],"source_label":"解题","source_breakdown":"解题7 / 合计7"},{"paper_id":"gaokao-ja-2007-national-standard","paper_label":"2007 全国卷","year":"2007","solving":7,"listening_prompt":0,"listening_transcript":0,"listening_asr":0,"total":7,"has_asr":false,"quality_flags":[],"source_label":"解题","source_breakdown":"解题7 / 合计7"},{"paper_id":"gaokao-ja-2020-national-standard","paper_label":"2020 全国卷","year":"2020","solving":7,"listening_prompt":0,"listening_transcript":0,"listening_asr":0,"total":7,"has_asr":false,"quality_flags":[],"source_label":"解题","source_breakdown":"解题7 / 合计7"},{"paper_id":"gaokao-ja-2022-national-standard","paper_label":"2022 全国卷","year":"2022","solving":7,"listening_prompt":0,"listening_transcript":0,"listening_asr":0,"total":7,"has_asr":false,"quality_flags":[],"source_label":"解题","source_breakdown":"解题7 / 合计7"},{"paper_id":"gaokao-ja-2008-national-standard","paper_label":"2008 全国卷","year":"2008","solving":6,"listening_prompt":0,"listening_transcript":0,"listening_asr":0,"total":6,"has_asr":false,"quality_flags":[],"source_label":"解题","source_breakdown":"解题6 / 合计6"},{"paper_id":"gaokao-ja-2017-national-standard","paper_label":"2017 全国卷","year":"2017","solving":6,"listening_prompt":0,"listening_transcript":0,"listening_asr":0,"total":6,"has_asr":false,"quality_flags":[],"source_label":"解题","source_breakdown":"解题6 / 合计6"},{"paper_id":"gaokao-ja-2018-national-standard","paper_label":"2018 全国卷","year":"2018","solving":6,"listening_prompt":0,"listening_transcript":0,"listening_asr":0,"total":6,"has_asr":false,"quality_flags":[],"source_label":"解题","source_breakdown":"解题6 / 合计6"},{"paper_id":"gaokao-ja-2023-national-standard","paper_label":"2023 全国卷","year":"2023","solving":5,"listening_prompt":0,"listening_transcript":1,"listening_asr":0,"total":6,"has_asr":false,"quality_flags":[],"source_label":"解题","source_breakdown":"解题5 / 文字稿1 / 合计6"},{"paper_id":"gaokao-ja-2001-national-standard","paper_label":"2001 全国卷","year":"2001","solving":5,"listening_prompt":0,"listening_transcript":0,"listening_asr":0,"total":5,"has_asr":false,"quality_flags":[],"source_label":"解题","source_breakdown":"解题5 / 合计5"},{"paper_id":"gaokao-ja-2005-national-standard","paper_label":"2005 全国卷","year":"2005","solving":5,"listening_prompt":0,"listening_transcript":0,"listening_asr":0,"total":5,"has_asr":false,"quality_flags":[],"source_label":"解题","source_breakdown":"解题5 / 合计5"},{"paper_id":"gaokao-ja-2010-national-standard","paper_label":"2010 全国卷","year":"2010","solving":5,"listening_prompt":0,"listening_transcript":0,"listening_asr":0,"total":5,"has_asr":false,"quality_flags":[],"source_label":"解题","source_breakdown":"解题5 / 合计5"},{"paper_id":"gaokao-ja-2013-national-standard","paper_label":"2013 全国卷","year":"2013","solving":5,"listening_prompt":0,"listening_transcript":0,"listening_asr":0,"total":5,"has_asr":false,"quality_flags":[],"source_label":"解题","source_breakdown":"解题5 / 合计5"},{"paper_id":"gaokao-ja-2016-national-standard","paper_label":"2016 全国卷","year":"2016","solving":5,"listening_prompt":0,"listening_transcript":0,"listening_asr":0,"total":5,"has_asr":false,"quality_flags":[],"source_label":"解题","source_breakdown":"解题5 / 合计5"},{"paper_id":"gaokao-ja-2019-national-standard","paper_label":"2019 全国卷","year":"2019","solving":5,"listening_prompt":0,"listening_transcript":0,"listening_asr":0,"total":5,"has_asr":false,"quality_flags":[],"source_label":"解题","source_breakdown":"解题5 / 合计5"},{"paper_id":"gaokao-ja-2024-national-new","paper_label":"2024 全国卷","year":"2024","solving":5,"listening_prompt":0,"listening_transcript":0,"listening_asr":0,"total":5,"has_asr":false,"quality_flags":[],"source_label":"解题","source_breakdown":"解题5 / 合计5"},{"paper_id":"gaokao-ja-2024-national-old","paper_label":"2024 全国卷","year":"2024","solving":5,"listening_prompt":0,"listening_transcript":0,"listening_asr":0,"total":5,"has_asr":false,"quality_flags":[],"source_label":"解题","source_breakdown":"解题5 / 合计5"},{"paper_id":"gaokao-ja-1998-national-standard","paper_label":"1998 全国卷","year":"1998","solving":4,"listening_prompt":0,"listening_transcript":0,"listening_asr":0,"total":4,"has_asr":false,"quality_flags":[],"source_label":"解题","source_breakdown":"解题4 / 合计4"},{"paper_id":"gaokao-ja-2012-national-standard","paper_label":"2012 全国卷","year":"2012","solving":4,"listening_prompt":0,"listening_transcript":0,"listening_asr":0,"total":4,"has_asr":false,"quality_flags":[],"source_label":"解题","source_breakdown":"解题4 / 合计4"},{"paper_id":"gaokao-ja-2021-national-standard","paper_label":"2021 全国卷","year":"2021","solving":4,"listening_prompt":0,"listening_transcript":0,"listening_asr":0,"total":4,"has_asr":false,"quality_flags":[],"source_label":"解题","source_breakdown":"解题4 / 合计4"},{"paper_id":"gaokao-ja-2006-national-standard","paper_label":"2006 全国卷","year":"2006","solving":3,"listening_prompt":0,"listening_transcript":0,"listening_asr":0,"total":3,"has_asr":false,"quality_flags":[],"source_label":"解题","source_breakdown":"解题3 / 合计3"},{"paper_id":"gaokao-ja-2025-national-standard","paper_label":"2025 全国卷","year":"2025","solving":2,"listening_prompt":0,"listening_transcript":0,"listening_asr":0,"total":2,"has_asr":false,"quality_flags":[],"source_label":"解题","source_breakdown":"解题2 / 合计2"}],"warnings":[]},"a89d815e5b3a5a76f1caee2d":{"word_id":"a89d815e5b3a5a76f1caee2d","display_form":"とても","lemma_form":"迚も","reading":"とても","pos_major":"副詞","pos_label":"副词","pos_bucket":"adverb","group":"content","group_label":"实词","counts":{"all":48,"total":48,"solving":41,"listening_prompt":1,"listening_transcript":1,"listening_asr":5,"listening_heard":6,"listening_total":7},"paper_counts":{"all":23,"solving":21,"listening_prompt":1,"listening_heard":6,"listening_total":7},"first_year":1998,"last_year":2025,"years_present":["1998","1999","2000","2001","2002","2003","2004","2005","2006","2007","2008","2010","2011","2012","2014","2015","2016","2018","2021","2022","2023","2024","2025"],"source_flags":["solving","listening_prompt","listening_transcript","listening_asr"],"has_asr":true,"quality_flags":[],"dict_query":"迚も","dict_query_alt":["とても"],"moji_url":"https://www.mojidict.com/searchText/%E8%BF%9A%E3%82%82","surface_variant_count":2,"reading_variant_count":2,"sense_ambiguous":false,"variants_preview":[["とても",47],["とっても",1]],"top_sources":[{"paper_id":"gaokao-ja-2007-national-standard","paper_label":"2007 全国卷","year":"2007","solving":4,"listening_prompt":0,"listening_transcript":0,"listening_asr":1,"total":5,"has_asr":true,"quality_flags":[],"source_label":"解题","source_breakdown":"解题4 / ASR1 / 合计5"},{"paper_id":"gaokao-ja-2002-national-standard","paper_label":"2002 全国卷","year":"2002","solving":3,"listening_prompt":0,"listening_transcript":0,"listening_asr":1,"total":4,"has_asr":true,"quality_flags":[],"source_label":"解题","source_breakdown":"解题3 / ASR1 / 合计4"},{"paper_id":"gaokao-ja-2008-national-standard","paper_label":"2008 全国卷","year":"2008","solving":4,"listening_prompt":0,"listening_transcript":0,"listening_asr":0,"total":4,"has_asr":false,"quality_flags":[],"source_label":"解题","source_breakdown":"解题4 / 合计4"}],"dictionary":{"source":"JMdict","headword":"迚も","reading":"とても","glosses":["very","awfully","exceedingly","(not) at all"],"parts":["adv"],"entry_id":"1008630"},"examples":[{"text":"日本では、若い女性に向かっておばさんと( )とても失礼になります。","paper_label":"1999 全国卷","paper_id":"gaokao-ja-1999-national-standard","year":"1999","source":"解题","has_asr":false},{"text":"今とても疲れていて、眠いんです。____その話は後にしてくれませんか。","paper_label":"2000 全国卷","paper_id":"gaokao-ja-2000-national-standard","year":"2000","source":"解题","has_asr":false},{"text":"これはとても大事なテストですから、( )間違いも許されません。","paper_label":"2001 全国卷","paper_id":"gaokao-ja-2001-national-standard","year":"2001","source":"解题","has_asr":false},{"text":"53 佐藤さんは動物が好きで、いろいろ飼っている。鳥も 、犬もいて、とてもにぎやかだ。","paper_label":"2002 全国卷","paper_id":"gaokao-ja-2002-national-standard","year":"2002","source":"解题","has_asr":false},{"text":"54 こんなたくさんのごちそう、わたし1人ではとても 。","paper_label":"2002 全国卷","paper_id":"gaokao-ja-2002-national-standard","year":"2002","source":"解题","has_asr":false},{"text":"その店の品物は___ほこりだらけで、とても売れそうにない。","paper_label":"2003 全国卷","paper_id":"gaokao-ja-2003-national-standard","year":"2003","source":"解题","has_asr":false}],"variant_counts":[["とても",47],["とっても",1]],"year_distribution":{"1998":1,"1999":2,"2000":2,"2001":1,"2002":4,"2003":1,"2004":2,"2005":3,"2006":3,"2007":5,"2008":4,"2010":1,"2011":1,"2012":2,"2014":1,"2015":1,"2016":4,"2018":1,"2021":2,"2022":2,"2023":1,"2024":2,"2025":2},"paper_distribution":[{"paper_id":"gaokao-ja-2007-national-standard","paper_label":"2007 全国卷","year":"2007","solving":4,"listening_prompt":0,"listening_transcript":0,"listening_asr":1,"total":5,"has_asr":true,"quality_flags":[],"source_label":"解题","source_breakdown":"解题4 / ASR1 / 合计5"},{"paper_id":"gaokao-ja-2002-national-standard","paper_label":"2002 全国卷","year":"2002","solving":3,"listening_prompt":0,"listening_transcript":0,"listening_asr":1,"total":4,"has_asr":true,"quality_flags":[],"source_label":"解题","source_breakdown":"解题3 / ASR1 / 合计4"},{"paper_id":"gaokao-ja-2008-national-standard","paper_label":"2008 全国卷","year":"2008","solving":4,"listening_prompt":0,"listening_transcript":0,"listening_asr":0,"total":4,"has_asr":false,"quality_flags":[],"source_label":"解题","source_breakdown":"解题4 / 合计4"},{"paper_id":"gaokao-ja-2016-national-standard","paper_label":"2016 全国卷","year":"2016","solving":4,"listening_prompt":0,"listening_transcript":0,"listening_asr":0,"total":4,"has_asr":false,"quality_flags":[],"source_label":"解题","source_breakdown":"解题4 / 合计4"},{"paper_id":"gaokao-ja-2005-national-standard","paper_label":"2005 全国卷","year":"2005","solving":3,"listening_prompt":0,"listening_transcript":0,"listening_asr":0,"total":3,"has_asr":false,"quality_flags":[],"source_label":"解题","source_breakdown":"解题3 / 合计3"},{"paper_id":"gaokao-ja-2006-national-standard","paper_label":"2006 全国卷","year":"2006","solving":2,"listening_prompt":0,"listening_transcript":0,"listening_asr":1,"total":3,"has_asr":true,"quality_flags":[],"source_label":"解题","source_breakdown":"解题2 / ASR1 / 合计3"},{"paper_id":"gaokao-ja-1999-national-standard","paper_label":"1999 全国卷","year":"1999","solving":2,"listening_prompt":0,"listening_transcript":0,"listening_asr":0,"total":2,"has_asr":false,"quality_flags":[],"source_label":"解题","source_breakdown":"解题2 / 合计2"},{"paper_id":"gaokao-ja-2000-national-standard","paper_label":"2000 全国卷","year":"2000","solving":2,"listening_prompt":0,"listening_transcript":0,"listening_asr":0,"total":2,"has_asr":false,"quality_flags":[],"source_label":"解题","source_breakdown":"解题2 / 合计2"},{"paper_id":"gaokao-ja-2004-national-standard","paper_label":"2004 全国卷","year":"2004","solving":2,"listening_prompt":0,"listening_transcript":0,"listening_asr":0,"total":2,"has_asr":false,"quality_flags":[],"source_label":"解题","source_breakdown":"解题2 / 合计2"},{"paper_id":"gaokao-ja-2012-national-standard","paper_label":"2012 全国卷","year":"2012","solving":1,"listening_prompt":0,"listening_transcript":0,"listening_asr":1,"total":2,"has_asr":true,"quality_flags":[],"source_label":"解题","source_breakdown":"解题1 / ASR1 / 合计2"},{"paper_id":"gaokao-ja-2021-national-standard","paper_label":"2021 全国卷","year":"2021","solving":2,"listening_prompt":0,"listening_transcript":0,"listening_asr":0,"total":2,"has_asr":false,"quality_flags":[],"source_label":"解题","source_breakdown":"解题2 / 合计2"},{"paper_id":"gaokao-ja-2022-national-standard","paper_label":"2022 全国卷","year":"2022","solving":2,"listening_prompt":0,"listening_transcript":0,"listening_asr":0,"total":2,"has_asr":false,"quality_flags":[],"source_label":"解题","source_breakdown":"解题2 / 合计2"},{"paper_id":"gaokao-ja-2024-national-old","paper_label":"2024 全国卷","year":"2024","solving":2,"listening_prompt":0,"listening_transcript":0,"listening_asr":0,"total":2,"has_asr":false,"quality_flags":[],"source_label":"解题","source_breakdown":"解题2 / 合计2"},{"paper_id":"gaokao-ja-2025-national-standard","paper_label":"2025 全国卷","year":"2025","solving":1,"listening_prompt":0,"listening_transcript":1,"listening_asr":0,"total":2,"has_asr":false,"quality_flags":[],"source_label":"解题","source_breakdown":"解题1 / 文字稿1 / 合计2"},{"paper_id":"gaokao-ja-1998-national-standard","paper_label":"1998 全国卷","year":"1998","solving":1,"listening_prompt":0,"listening_transcript":0,"listening_asr":0,"total":1,"has_asr":false,"quality_flags":[],"source_label":"解题","source_breakdown":"解题1 / 合计1"},{"paper_id":"gaokao-ja-2001-national-standard","paper_label":"2001 全国卷","year":"2001","solving":1,"listening_prompt":0,"listening_transcript":0,"listening_asr":0,"total":1,"has_asr":false,"quality_flags":[],"source_label":"解题","source_breakdown":"解题1 / 合计1"},{"paper_id":"gaokao-ja-2003-national-standard","paper_label":"2003 全国卷","year":"2003","solving":1,"listening_prompt":0,"listening_transcript":0,"listening_asr":0,"total":1,"has_asr":false,"quality_flags":[],"source_label":"解题","source_breakdown":"解题1 / 合计1"},{"paper_id":"gaokao-ja-2010-national-standard","paper_label":"2010 全国卷","year":"2010","solving":1,"listening_prompt":0,"listening_transcript":0,"listening_asr":0,"total":1,"has_asr":false,"quality_flags":[],"source_label":"解题","source_breakdown":"解题1 / 合计1"},{"paper_id":"gaokao-ja-2011-national-standard","paper_label":"2011 全国卷","year":"2011","solving":1,"listening_prompt":0,"listening_transcript":0,"listening_asr":0,"total":1,"has_asr":false,"quality_flags":[],"source_label":"解题","source_breakdown":"解题1 / 合计1"},{"paper_id":"gaokao-ja-2014-national-standard","paper_label":"2014 全国卷","year":"2014","solving":0,"listening_prompt":0,"listening_transcript":0,"listening_asr":1,"total":1,"has_asr":true,"quality_flags":[],"source_label":"听力 ASR","source_breakdown":"ASR1 / 合计1"},{"paper_id":"gaokao-ja-2015-national-standard","paper_label":"2015 全国卷","year":"2015","solving":0,"listening_prompt":1,"listening_transcript":0,"listening_asr":0,"total":1,"has_asr":false,"quality_flags":[],"source_label":"听力题面","source_breakdown":"题面1 / 合计1"},{"paper_id":"gaokao-ja-2018-national-standard","paper_label":"2018 全国卷","year":"2018","solving":1,"listening_prompt":0,"listening_transcript":0,"listening_asr":0,"total":1,"has_asr":false,"quality_flags":[],"source_label":"解题","source_breakdown":"解题1 / 合计1"},{"paper_id":"gaokao-ja-2023-national-standard","paper_label":"2023 全国卷","year":"2023","solving":1,"listening_prompt":0,"listening_transcript":0,"listening_asr":0,"total":1,"has_asr":false,"quality_flags":[],"source_label":"解题","source_breakdown":"解题1 / 合计1"}],"warnings":["contains_asr","lookup_by_dictionary_form_recommended"]},"a8c41ee245b16fb1dc443f0f":{"word_id":"a8c41ee245b16fb1dc443f0f","display_form":"道路","lemma_form":"道路","reading":"どうろ","pos_major":"名詞","pos_label":"名词","pos_bucket":"noun","group":"content","group_label":"实词","counts":{"all":20,"total":20,"solving":17,"listening_prompt":2,"listening_transcript":0,"listening_asr":1,"listening_heard":1,"listening_total":3},"paper_counts":{"all":8,"solving":5,"listening_prompt":2,"listening_heard":1,"listening_total":3},"first_year":2003,"last_year":2024,"years_present":["2003","2006","2007","2010","2011","2017","2022","2024"],"source_flags":["solving","listening_prompt","listening_asr"],"has_asr":true,"quality_flags":[],"dict_query":"道路","dict_query_alt":["どうろ"],"moji_url":"https://www.mojidict.com/searchText/%E9%81%93%E8%B7%AF","surface_variant_count":1,"reading_variant_count":1,"sense_ambiguous":false,"variants_preview":[["道路",20]],"top_sources":[{"paper_id":"gaokao-ja-2007-national-standard","paper_label":"2007 全国卷","year":"2007","solving":8,"listening_prompt":0,"listening_transcript":0,"listening_asr":0,"total":8,"has_asr":false,"quality_flags":[],"source_label":"解题","source_breakdown":"解题8 / 合计8"},{"paper_id":"gaokao-ja-2010-national-standard","paper_label":"2010 全国卷","year":"2010","solving":4,"listening_prompt":0,"listening_transcript":0,"listening_asr":0,"total":4,"has_asr":false,"quality_flags":[],"source_label":"解题","source_breakdown":"解题4 / 合计4"},{"paper_id":"gaokao-ja-2017-national-standard","paper_label":"2017 全国卷","year":"2017","solving":2,"listening_prompt":0,"listening_transcript":0,"listening_asr":0,"total":2,"has_asr":false,"quality_flags":[],"source_label":"解题","source_breakdown":"解题2 / 合计2"}],"dictionary":{"source":"JMdict","headword":"道路","reading":"どうろ","glosses":["road","highway"],"parts":["n"],"entry_id":"1454290"},"examples":[{"text":"文中に「道路を探した」とあるが,その原因はどれか。","paper_label":"2007 全国卷","paper_id":"gaokao-ja-2007-national-standard","year":"2007","source":"解题","has_asr":false},{"text":"A 泥棒が道路に捨てたと聞いたから B 娘が道路に捨てたと聞いたから","paper_label":"2007 全国卷","paper_id":"gaokao-ja-2007-national-standard","year":"2007","source":"解题","has_asr":false},{"text":"C 妻が道路に落としたと聞いたから D 風で道路に飛んでしまったと聞いたから","paper_label":"2007 全国卷","paper_id":"gaokao-ja-2007-national-standard","year":"2007","source":"解题","has_asr":false},{"text":"C.車の多く通る道路 D.原っぱや空き地、車が少なかった道路","paper_label":"2010 全国卷","paper_id":"gaokao-ja-2010-national-standard","year":"2010","source":"解题","has_asr":false},{"text":"A. 男の子が道路に走っていったから","paper_label":"2017 全国卷","paper_id":"gaokao-ja-2017-national-standard","year":"2017","source":"解题","has_asr":false},{"text":"A 道路と建物 B 人々の歩き方 C 自然の変わり方","paper_label":"2011 全国卷","paper_id":"gaokao-ja-2011-national-standard","year":"2011","source":"听力题面","has_asr":false}],"variant_counts":[["道路",20]],"year_distribution":{"2003":1,"2006":1,"2007":8,"2010":4,"2011":1,"2017":2,"2022":1,"2024":2},"paper_distribution":[{"paper_id":"gaokao-ja-2007-national-standard","paper_label":"2007 全国卷","year":"2007","solving":8,"listening_prompt":0,"listening_transcript":0,"listening_asr":0,"total":8,"has_asr":false,"quality_flags":[],"source_label":"解题","source_breakdown":"解题8 / 合计8"},{"paper_id":"gaokao-ja-2010-national-standard","paper_label":"2010 全国卷","year":"2010","solving":4,"listening_prompt":0,"listening_transcript":0,"listening_asr":0,"total":4,"has_asr":false,"quality_flags":[],"source_label":"解题","source_breakdown":"解题4 / 合计4"},{"paper_id":"gaokao-ja-2017-national-standard","paper_label":"2017 全国卷","year":"2017","solving":2,"listening_prompt":0,"listening_transcript":0,"listening_asr":0,"total":2,"has_asr":false,"quality_flags":[],"source_label":"解题","source_breakdown":"解题2 / 合计2"},{"paper_id":"gaokao-ja-2024-national-new","paper_label":"2024 全国卷","year":"2024","solving":2,"listening_prompt":0,"listening_transcript":0,"listening_asr":0,"total":2,"has_asr":false,"quality_flags":[],"source_label":"解题","source_breakdown":"解题2 / 合计2"},{"paper_id":"gaokao-ja-2003-national-standard","paper_label":"2003 全国卷","year":"2003","solving":1,"listening_prompt":0,"listening_transcript":0,"listening_asr":0,"total":1,"has_asr":false,"quality_flags":[],"source_label":"解题","source_breakdown":"解题1 / 合计1"},{"paper_id":"gaokao-ja-2006-national-standard","paper_label":"2006 全国卷","year":"2006","solving":0,"listening_prompt":0,"listening_transcript":0,"listening_asr":1,"total":1,"has_asr":true,"quality_flags":[],"source_label":"听力 ASR","source_breakdown":"ASR1 / 合计1"},{"paper_id":"gaokao-ja-2011-national-standard","paper_label":"2011 全国卷","year":"2011","solving":0,"listening_prompt":1,"listening_transcript":0,"listening_asr":0,"total":1,"has_asr":false,"quality_flags":[],"source_label":"听力题面","source_breakdown":"题面1 / 合计1"},{"paper_id":"gaokao-ja-2022-national-standard","paper_label":"2022 全国卷","year":"2022","solving":0,"listening_prompt":1,"listening_transcript":0,"listening_asr":0,"total":1,"has_asr":false,"quality_flags":[],"source_label":"听力题面","source_breakdown":"题面1 / 合计1"}],"warnings":["contains_asr"]},"a812fc9284824e868052a5bc":{"word_id":"a812fc9284824e868052a5bc","display_form":"もしもし","lemma_form":"もしもし","reading":"もしもし","pos_major":"感動詞","pos_label":"感动词","pos_bucket":"interjection","group":"content","group_label":"实词","counts":{"all":14,"total":14,"solving":2,"listening_prompt":0,"listening_transcript":3,"listening_asr":9,"listening_heard":12,"listening_total":12},"paper_counts":{"all":10,"solving":2,"listening_prompt":0,"listening_heard":8,"listening_total":8},"first_year":2001,"last_year":2023,"years_present":["2001","2002","2003","2007","2009","2010","2014","2015","2020","2023"],"source_flags":["solving","listening_transcript","listening_asr"],"has_asr":true,"quality_flags":[],"dict_query":"もしもし","dict_query_alt":[],"moji_url":"https://www.mojidict.com/searchText/%E3%82%82%E3%81%97%E3%82%82%E3%81%97","surface_variant_count":1,"reading_variant_count":1,"sense_ambiguous":false,"variants_preview":[["もしもし",14]],"top_sources":[{"paper_id":"gaokao-ja-2023-national-standard","paper_label":"2023 全国卷","year":"2023","solving":0,"listening_prompt":0,"listening_transcript":3,"listening_asr":0,"total":3,"has_asr":false,"quality_flags":[],"source_label":"听力文字稿","source_breakdown":"文字稿3 / 合计3"},{"paper_id":"gaokao-ja-2007-national-standard","paper_label":"2007 全国卷","year":"2007","solving":0,"listening_prompt":0,"listening_transcript":0,"listening_asr":2,"total":2,"has_asr":true,"quality_flags":[],"source_label":"听力 ASR","source_breakdown":"ASR2 / 合计2"},{"paper_id":"gaokao-ja-2014-national-standard","paper_label":"2014 全国卷","year":"2014","solving":0,"listening_prompt":0,"listening_transcript":0,"listening_asr":2,"total":2,"has_asr":true,"quality_flags":[],"source_label":"听力 ASR","source_breakdown":"ASR2 / 合计2"}],"dictionary":{"source":"JMdict","headword":"もしもし","reading":"もしもし","glosses":["hello (e.g. on phone)","excuse me! (when calling out to someone)"],"parts":["int"],"entry_id":"1012550"},"examples":[{"text":"もしもし、空港へ行きたいのですが、タクシーを___お願いします。","paper_label":"2020 全国卷","paper_id":"gaokao-ja-2020-national-standard","year":"2020","source":"解题","has_asr":false},{"text":"女:もしもし。あっ、武君、久しぶり。","paper_label":"2023 全国卷","paper_id":"gaokao-ja-2023-national-standard","year":"2023","source":"听力文字稿","has_asr":false},{"text":"A、間違い電話でした B、「もしもし」と言いましょう","paper_label":"2001 全国卷","paper_id":"gaokao-ja-2001-national-standard","year":"2001","source":"解题","has_asr":false},{"text":"もしもし 今迷っ て いる の で、もう一度住所教えて いただけ ません か。","paper_label":"2002 全国卷","paper_id":"gaokao-ja-2002-national-standard","year":"2002","source":"听力 ASR","has_asr":true},{"text":"もしもし 田中 さん はいらっしゃいますか すい ません が、山田 さん だけ です お 願い し ます。","paper_label":"2003 全国卷","paper_id":"gaokao-ja-2003-national-standard","year":"2003","source":"听力 ASR","has_asr":true},{"text":"もしもし 王さん、どう したん ですか 30 分も 前 から 待っ て いる ん です よ。","paper_label":"2007 全国卷","paper_id":"gaokao-ja-2007-national-standard","year":"2007","source":"听力 ASR","has_asr":true}],"variant_counts":[["もしもし",14]],"year_distribution":{"2001":1,"2002":1,"2003":1,"2007":2,"2009":1,"2010":1,"2014":2,"2015":1,"2020":1,"2023":3},"paper_distribution":[{"paper_id":"gaokao-ja-2023-national-standard","paper_label":"2023 全国卷","year":"2023","solving":0,"listening_prompt":0,"listening_transcript":3,"listening_asr":0,"total":3,"has_asr":false,"quality_flags":[],"source_label":"听力文字稿","source_breakdown":"文字稿3 / 合计3"},{"paper_id":"gaokao-ja-2007-national-standard","paper_label":"2007 全国卷","year":"2007","solving":0,"listening_prompt":0,"listening_transcript":0,"listening_asr":2,"total":2,"has_asr":true,"quality_flags":[],"source_label":"听力 ASR","source_breakdown":"ASR2 / 合计2"},{"paper_id":"gaokao-ja-2014-national-standard","paper_label":"2014 全国卷","year":"2014","solving":0,"listening_prompt":0,"listening_transcript":0,"listening_asr":2,"total":2,"has_asr":true,"quality_flags":[],"source_label":"听力 ASR","source_breakdown":"ASR2 / 合计2"},{"paper_id":"gaokao-ja-2001-national-standard","paper_label":"2001 全国卷","year":"2001","solving":1,"listening_prompt":0,"listening_transcript":0,"listening_asr":0,"total":1,"has_asr":false,"quality_flags":[],"source_label":"解题","source_breakdown":"解题1 / 合计1"},{"paper_id":"gaokao-ja-2002-national-standard","paper_label":"2002 全国卷","year":"2002","solving":0,"listening_prompt":0,"listening_transcript":0,"listening_asr":1,"total":1,"has_asr":true,"quality_flags":[],"source_label":"听力 ASR","source_breakdown":"ASR1 / 合计1"},{"paper_id":"gaokao-ja-2003-national-standard","paper_label":"2003 全国卷","year":"2003","solving":0,"listening_prompt":0,"listening_transcript":0,"listening_asr":1,"total":1,"has_asr":true,"quality_flags":[],"source_label":"听力 ASR","source_breakdown":"ASR1 / 合计1"},{"paper_id":"gaokao-ja-2009-national-standard","paper_label":"2009 全国卷","year":"2009","solving":0,"listening_prompt":0,"listening_transcript":0,"listening_asr":1,"total":1,"has_asr":true,"quality_flags":[],"source_label":"听力 ASR","source_breakdown":"ASR1 / 合计1"},{"paper_id":"gaokao-ja-2010-national-standard","paper_label":"2010 全国卷","year":"2010","solving":0,"listening_prompt":0,"listening_transcript":0,"listening_asr":1,"total":1,"has_asr":true,"quality_flags":[],"source_label":"听力 ASR","source_breakdown":"ASR1 / 合计1"},{"paper_id":"gaokao-ja-2015-national-standard","paper_label":"2015 全国卷","year":"2015","solving":0,"listening_prompt":0,"listening_transcript":0,"listening_asr":1,"total":1,"has_asr":true,"quality_flags":[],"source_label":"听力 ASR","source_breakdown":"ASR1 / 合计1"},{"paper_id":"gaokao-ja-2020-national-standard","paper_label":"2020 全国卷","year":"2020","solving":1,"listening_prompt":0,"listening_transcript":0,"listening_asr":0,"total":1,"has_asr":false,"quality_flags":[],"source_label":"解题","source_breakdown":"解题1 / 合计1"}],"warnings":["contains_asr"]},"a8978ac03e406aeda9825d3e":{"word_id":"a8978ac03e406aeda9825d3e","display_form":"ゴミ","lemma_form":"ゴミ","reading":"ごみ","pos_major":"名詞","pos_label":"名词","pos_bucket":"noun","group":"content","group_label":"实词","counts":{"all":13,"total":13,"solving":0,"listening_prompt":1,"listening_transcript":2,"listening_asr":10,"listening_heard":12,"listening_total":13},"paper_counts":{"all":5,"solving":0,"listening_prompt":1,"listening_heard":5,"listening_total":5},"first_year":2013,"last_year":2024,"years_present":["2013","2017","2019","2022","2024"],"source_flags":["listening_prompt","listening_transcript","listening_asr"],"has_asr":true,"quality_flags":[],"dict_query":"ゴミ","dict_query_alt":["ごみ"],"moji_url":"https://www.mojidict.com/searchText/%E3%82%B4%E3%83%9F","surface_variant_count":1,"reading_variant_count":1,"sense_ambiguous":false,"variants_preview":[["ゴミ",13]],"top_sources":[{"paper_id":"gaokao-ja-2013-national-standard","paper_label":"2013 全国卷","year":"2013","solving":0,"listening_prompt":0,"listening_transcript":0,"listening_asr":6,"total":6,"has_asr":true,"quality_flags":[],"source_label":"听力 ASR","source_breakdown":"ASR6 / 合计6"},{"paper_id":"gaokao-ja-2019-national-standard","paper_label":"2019 全国卷","year":"2019","solving":0,"listening_prompt":0,"listening_transcript":0,"listening_asr":3,"total":3,"has_asr":true,"quality_flags":[],"source_label":"听力 ASR","source_breakdown":"ASR3 / 合计3"},{"paper_id":"gaokao-ja-2024-national-old","paper_label":"2024 全国卷","year":"2024","solving":0,"listening_prompt":1,"listening_transcript":1,"listening_asr":0,"total":2,"has_asr":false,"quality_flags":[],"source_label":"听力题面","source_breakdown":"题面1 / 文字稿1 / 合计2"}],"dictionary":{"source":"JMdict","headword":"ゴミ","reading":"ゴミ","glosses":["rubbish","trash","garbage","refuse"],"parts":["n"],"entry_id":"1369900"},"examples":[{"text":"女:玄関にあるゴミは邪魔ですね。今出してきます。","paper_label":"2024 全国卷","paper_id":"gaokao-ja-2024-national-old","year":"2024","source":"听力文字稿","has_asr":false},{"text":"まず燃えるゴミと燃えないゴミに分けておいてくださいね。","paper_label":"2013 全国卷","paper_id":"gaokao-ja-2013-national-standard","year":"2013","source":"听力 ASR","has_asr":true},{"text":"燃えるゴミは明日ですが、燃えないゴミは明後日です。","paper_label":"2013 全国卷","paper_id":"gaokao-ja-2013-national-standard","year":"2013","source":"听力 ASR","has_asr":true},{"text":"なぜなら、自分の出したゴミを持ち帰るのが、自分の行動に責任を持つことだと考えるからです。","paper_label":"2019 全国卷","paper_id":"gaokao-ja-2019-national-standard","year":"2019","source":"听力 ASR","has_asr":true},{"text":"捨てられたゴミで他の人の仕事が増えます。","paper_label":"2019 全国卷","paper_id":"gaokao-ja-2019-national-standard","year":"2019","source":"听力 ASR","has_asr":true},{"text":"B. ゴミを出してくる。","paper_label":"2024 全国卷","paper_id":"gaokao-ja-2024-national-old","year":"2024","source":"听力题面","has_asr":false}],"variant_counts":[["ゴミ",13]],"year_distribution":{"2013":6,"2017":1,"2019":3,"2022":1,"2024":2},"paper_distribution":[{"paper_id":"gaokao-ja-2013-national-standard","paper_label":"2013 全国卷","year":"2013","solving":0,"listening_prompt":0,"listening_transcript":0,"listening_asr":6,"total":6,"has_asr":true,"quality_flags":[],"source_label":"听力 ASR","source_breakdown":"ASR6 / 合计6"},{"paper_id":"gaokao-ja-2019-national-standard","paper_label":"2019 全国卷","year":"2019","solving":0,"listening_prompt":0,"listening_transcript":0,"listening_asr":3,"total":3,"has_asr":true,"quality_flags":[],"source_label":"听力 ASR","source_breakdown":"ASR3 / 合计3"},{"paper_id":"gaokao-ja-2024-national-old","paper_label":"2024 全国卷","year":"2024","solving":0,"listening_prompt":1,"listening_transcript":1,"listening_asr":0,"total":2,"has_asr":false,"quality_flags":[],"source_label":"听力题面","source_breakdown":"题面1 / 文字稿1 / 合计2"},{"paper_id":"gaokao-ja-2017-national-standard","paper_label":"2017 全国卷","year":"2017","solving":0,"listening_prompt":0,"listening_transcript":0,"listening_asr":1,"total":1,"has_asr":true,"quality_flags":[],"source_label":"听力 ASR","source_breakdown":"ASR1 / 合计1"},{"paper_id":"gaokao-ja-2022-national-standard","paper_label":"2022 全国卷","year":"2022","solving":0,"listening_prompt":0,"listening_transcript":1,"listening_asr":0,"total":1,"has_asr":false,"quality_flags":[],"source_label":"听力文字稿","source_breakdown":"文字稿1 / 合计1"}],"warnings":["contains_asr"]},"a87fca7516ce6ec6cb6c0b38":{"word_id":"a87fca7516ce6ec6cb6c0b38","display_form":"忘却","lemma_form":"忘却","reading":"ぼうきゃく","pos_major":"名詞","pos_label":"名词","pos_bucket":"noun","group":"content","group_label":"实词","counts":{"all":4,"total":4,"solving":4,"listening_prompt":0,"listening_transcript":0,"listening_asr":0,"listening_heard":0,"listening_total":0},"paper_counts":{"all":1,"solving":1,"listening_prompt":0,"listening_heard":0,"listening_total":0},"first_year":2019,"last_year":2019,"years_present":["2019"],"source_flags":["solving"],"has_asr":false,"quality_flags":[],"dict_query":"忘却","dict_query_alt":["ぼうきゃく"],"moji_url":"https://www.mojidict.com/searchText/%E5%BF%98%E5%8D%B4","surface_variant_count":1,"reading_variant_count":1,"sense_ambiguous":false,"variants_preview":[["忘却",4]],"top_sources":[{"paper_id":"gaokao-ja-2019-national-standard","paper_label":"2019 全国卷","year":"2019","solving":4,"listening_prompt":0,"listening_transcript":0,"listening_asr":0,"total":4,"has_asr":false,"quality_flags":[],"source_label":"解题","source_breakdown":"解题4 / 合计4"}],"dictionary":{"source":"JMdict","headword":"忘却","reading":"ぼうきゃく","glosses":["lapse of memory","forgetting completely","(consigning to) oblivion"],"parts":["n","vs","vt"],"entry_id":"1519260"},"examples":[{"text":"この工場の整理に当たるのが忘却である。人間の頭を倉庫として見る場合,忘却は危険だが,人間の頭を工場としてみる場合,能率をよくしようと思えば,どんどん忘れることが必要である。","paper_label":"2019 全国卷","paper_id":"gaokao-ja-2019-national-standard","year":"2019","source":"解题","has_asr":false},{"text":"B.知識を勉強する時,忘却が必要である。","paper_label":"2019 全国卷","paper_id":"gaokao-ja-2019-national-standard","year":"2019","source":"解题","has_asr":false},{"text":"C.知識を整理する時,忘却も必要である。","paper_label":"2019 全国卷","paper_id":"gaokao-ja-2019-national-standard","year":"2019","source":"解题","has_asr":false}],"variant_counts":[["忘却",4]],"year_distribution":{"2019":4},"paper_distribution":[{"paper_id":"gaokao-ja-2019-national-standard","paper_label":"2019 全国卷","year":"2019","solving":4,"listening_prompt":0,"listening_transcript":0,"listening_asr":0,"total":4,"has_asr":false,"quality_flags":[],"source_label":"解题","source_breakdown":"解题4 / 合计4"}],"warnings":[]},"a8a2285f3e4f286efed80edd":{"word_id":"a8a2285f3e4f286efed80edd","display_form":"崩し","lemma_form":"崩す","reading":"くずし","pos_major":"動詞","pos_label":"动词","pos_bucket":"verb","group":"content","group_label":"实词","counts":{"all":2,"total":2,"solving":2,"listening_prompt":0,"listening_transcript":0,"listening_asr":0,"listening_heard":0,"listening_total":0},"paper_counts":{"all":2,"solving":2,"listening_prompt":0,"listening_heard":0,"listening_total":0},"first_year":2002,"last_year":2022,"years_present":["2002","2022"],"source_flags":["solving"],"has_asr":false,"quality_flags":[],"dict_query":"崩す","dict_query_alt":["崩し","くずし"],"moji_url":"https://www.mojidict.com/searchText/%E5%B4%A9%E3%81%99","surface_variant_count":1,"reading_variant_count":1,"sense_ambiguous":false,"variants_preview":[["崩し",2]],"top_sources":[{"paper_id":"gaokao-ja-2002-national-standard","paper_label":"2002 全国卷","year":"2002","solving":1,"listening_prompt":0,"listening_transcript":0,"listening_asr":0,"total":1,"has_asr":false,"quality_flags":[],"source_label":"解题","source_breakdown":"解题1 / 合计1"},{"paper_id":"gaokao-ja-2022-national-standard","paper_label":"2022 全国卷","year":"2022","solving":1,"listening_prompt":0,"listening_transcript":0,"listening_asr":0,"total":1,"has_asr":false,"quality_flags":[],"source_label":"解题","source_breakdown":"解题1 / 合计1"}],"dictionary":{"source":"JMdict","headword":"崩す","reading":"くずす","glosses":["to destroy","to demolish","to pull down","to tear down"],"parts":["v5s","vt"],"entry_id":"1516260"},"examples":[{"text":"21 二、三年のうちに、この山を崩して、スキー場 する計画がある。","paper_label":"2002 全国卷","paper_id":"gaokao-ja-2002-national-standard","year":"2002","source":"解题","has_asr":false},{"text":"…寝不足がいつの間にか借金のように膨らんで,健康や仕事に悪影響を及ぼす。「睡眠負債」というやつである。たまった借りを一括返済しようと休日に寝だめをしても,かえってリズムが乱れ体調を崩してしまう。","paper_label":"2022 全国卷","paper_id":"gaokao-ja-2022-national-standard","year":"2022","source":"解题","has_asr":false}],"variant_counts":[["崩し",2]],"year_distribution":{"2002":1,"2022":1},"paper_distribution":[{"paper_id":"gaokao-ja-2002-national-standard","paper_label":"2002 全国卷","year":"2002","solving":1,"listening_prompt":0,"listening_transcript":0,"listening_asr":0,"total":1,"has_asr":false,"quality_flags":[],"source_label":"解题","source_breakdown":"解题1 / 合计1"},{"paper_id":"gaokao-ja-2022-national-standard","paper_label":"2022 全国卷","year":"2022","solving":1,"listening_prompt":0,"listening_transcript":0,"listening_asr":0,"total":1,"has_asr":false,"quality_flags":[],"source_label":"解题","source_breakdown":"解题1 / 合计1"}],"warnings":["lookup_by_dictionary_form_recommended"]},"a8d613353bbb1c7f62394bde":{"word_id":"a8d613353bbb1c7f62394bde","display_form":"性質","lemma_form":"性質","reading":"せいしつ","pos_major":"名詞","pos_label":"名词","pos_bucket":"noun","group":"content","group_label":"实词","counts":{"all":2,"total":2,"solving":2,"listening_prompt":0,"listening_transcript":0,"listening_asr":0,"listening_heard":0,"listening_total":0},"paper_counts":{"all":2,"solving":2,"listening_prompt":0,"listening_heard":0,"listening_total":0},"first_year":2007,"last_year":2015,"years_present":["2007","2015"],"source_flags":["solving"],"has_asr":false,"quality_flags":[],"dict_query":"性質","dict_query_alt":["せいしつ"],"moji_url":"https://www.mojidict.com/searchText/%E6%80%A7%E8%B3%AA","surface_variant_count":1,"reading_variant_count":1,"sense_ambiguous":false,"variants_preview":[["性質",2]],"top_sources":[{"paper_id":"gaokao-ja-2007-national-standard","paper_label":"2007 全国卷","year":"2007","solving":1,"listening_prompt":0,"listening_transcript":0,"listening_asr":0,"total":1,"has_asr":false,"quality_flags":[],"source_label":"解题","source_breakdown":"解题1 / 合计1"},{"paper_id":"gaokao-ja-2015-national-standard","paper_label":"2015 全国卷","year":"2015","solving":1,"listening_prompt":0,"listening_transcript":0,"listening_asr":0,"total":1,"has_asr":false,"quality_flags":[],"source_label":"解题","source_breakdown":"解题1 / 合计1"}],"dictionary":{"source":"JMdict","headword":"性質","reading":"せいしつ","glosses":["nature (of a person)","disposition","temperament","character"],"parts":["n"],"entry_id":"1375390"},"examples":[{"text":"地球温暖化の問題というのは,従来の公害とはまったく違う性質のものと言わなければならないでしょう。と言いますのは,公害と言われるものの多くは,有害物質を如何に除去するかという点が問題になるわけで…","paper_label":"2007 全国卷","paper_id":"gaokao-ja-2007-national-standard","year":"2007","source":"解题","has_asr":false},{"text":"…・擬態語は、発音と意味の結びを変えることができない。発音が意味を決めているからである。こうした性質は次のようなおもしろいことを起こす。それは、ある音が決まった意味に直結する傾向である。たとえば…","paper_label":"2015 全国卷","paper_id":"gaokao-ja-2015-national-standard","year":"2015","source":"解题","has_asr":false}],"variant_counts":[["性質",2]],"year_distribution":{"2007":1,"2015":1},"paper_distribution":[{"paper_id":"gaokao-ja-2007-national-standard","paper_label":"2007 全国卷","year":"2007","solving":1,"listening_prompt":0,"listening_transcript":0,"listening_asr":0,"total":1,"has_asr":false,"quality_flags":[],"source_label":"解题","source_breakdown":"解题1 / 合计1"},{"paper_id":"gaokao-ja-2015-national-standard","paper_label":"2015 全国卷","year":"2015","solving":1,"listening_prompt":0,"listening_transcript":0,"listening_asr":0,"total":1,"has_asr":false,"quality_flags":[],"source_label":"解题","source_breakdown":"解题1 / 合计1"}],"warnings":[]},"a812192021059541881572d0":{"word_id":"a812192021059541881572d0","display_form":"神戸","lemma_form":"神戸","reading":"こうべ","pos_major":"名詞","pos_label":"名词","pos_bucket":"noun","group":"content","group_label":"实词","counts":{"all":2,"total":2,"solving":2,"listening_prompt":0,"listening_transcript":0,"listening_asr":0,"listening_heard":0,"listening_total":0},"paper_counts":{"all":2,"solving":2,"listening_prompt":0,"listening_heard":0,"listening_total":0},"first_year":2001,"last_year":2005,"years_present":["2001","2005"],"source_flags":["solving"],"has_asr":false,"quality_flags":[],"dict_query":"神戸","dict_query_alt":["こうべ"],"moji_url":"https://www.mojidict.com/searchText/%E7%A5%9E%E6%88%B8","surface_variant_count":1,"reading_variant_count":1,"sense_ambiguous":false,"variants_preview":[["神戸",2]],"top_sources":[{"paper_id":"gaokao-ja-2001-national-standard","paper_label":"2001 全国卷","year":"2001","solving":1,"listening_prompt":0,"listening_transcript":0,"listening_asr":0,"total":1,"has_asr":false,"quality_flags":[],"source_label":"解题","source_breakdown":"解题1 / 合计1"},{"paper_id":"gaokao-ja-2005-national-standard","paper_label":"2005 全国卷","year":"2005","solving":1,"listening_prompt":0,"listening_transcript":0,"listening_asr":0,"total":1,"has_asr":false,"quality_flags":[],"source_label":"解题","source_breakdown":"解题1 / 合计1"}],"dictionary":{"source":"JMdict","headword":"神戸","reading":"こうべ","glosses":["Kobe (city)"],"parts":["n"],"entry_id":"2164600"},"examples":[{"text":"日本の行政区画は一都一府43県からなっているが、その2府とは大阪府と( )府のことを指す。 A、京都 B、横浜 C、神戸 D、名古屋","paper_label":"2001 全国卷","paper_id":"gaokao-ja-2001-national-standard","year":"2001","source":"解题","has_asr":false},{"text":"A神戸 B名古屋 C横浜 D東京","paper_label":"2005 全国卷","paper_id":"gaokao-ja-2005-national-standard","year":"2005","source":"解题","has_asr":false}],"variant_counts":[["神戸",2]],"year_distribution":{"2001":1,"2005":1},"paper_distribution":[{"paper_id":"gaokao-ja-2001-national-standard","paper_label":"2001 全国卷","year":"2001","solving":1,"listening_prompt":0,"listening_transcript":0,"listening_asr":0,"total":1,"has_asr":false,"quality_flags":[],"source_label":"解题","source_breakdown":"解题1 / 合计1"},{"paper_id":"gaokao-ja-2005-national-standard","paper_label":"2005 全国卷","year":"2005","solving":1,"listening_prompt":0,"listening_transcript":0,"listening_asr":0,"total":1,"has_asr":false,"quality_flags":[],"source_label":"解题","source_breakdown":"解题1 / 合计1"}],"warnings":[]},"a8c83c99843462ede1a2736b":{"word_id":"a8c83c99843462ede1a2736b","display_form":"結婚式","lemma_form":"結婚式","reading":"けっこんしき","pos_major":"名詞","pos_label":"名词","pos_bucket":"noun","group":"content","group_label":"实词","counts":{"all":2,"total":2,"solving":0,"listening_prompt":1,"listening_transcript":0,"listening_asr":1,"listening_heard":1,"listening_total":2},"paper_counts":{"all":1,"solving":0,"listening_prompt":1,"listening_heard":1,"listening_total":1},"first_year":2015,"last_year":2015,"years_present":["2015"],"source_flags":["listening_prompt","listening_asr"],"has_asr":true,"quality_flags":[],"dict_query":"結婚式","dict_query_alt":["けっこんしき"],"moji_url":"https://www.mojidict.com/searchText/%E7%B5%90%E5%A9%9A%E5%BC%8F","surface_variant_count":1,"reading_variant_count":1,"sense_ambiguous":false,"variants_preview":[["結婚式",2]],"top_sources":[{"paper_id":"gaokao-ja-2015-national-standard","paper_label":"2015 全国卷","year":"2015","solving":0,"listening_prompt":1,"listening_transcript":0,"listening_asr":1,"total":2,"has_asr":true,"quality_flags":[],"source_label":"听力题面","source_breakdown":"题面1 / ASR1 / 合计2"}],"dictionary":{"source":"JMdict","headword":"結婚式","reading":"けっこんしき","glosses":["marriage ceremony","wedding","nuptials"],"parts":["n"],"entry_id":"1254810"},"examples":[{"text":"あの日本では結婚式のお祝い、普通いくらぐらいですか?","paper_label":"2015 全国卷","paper_id":"gaokao-ja-2015-national-standard","year":"2015","source":"听力 ASR","has_asr":true},{"text":"結婚式のお祝いはどのぐらいですか。","paper_label":"2015 全国卷","paper_id":"gaokao-ja-2015-national-standard","year":"2015","source":"听力题面","has_asr":false}],"variant_counts":[["結婚式",2]],"year_distribution":{"2015":2},"paper_distribution":[{"paper_id":"gaokao-ja-2015-national-standard","paper_label":"2015 全国卷","year":"2015","solving":0,"listening_prompt":1,"listening_transcript":0,"listening_asr":1,"total":2,"has_asr":true,"quality_flags":[],"source_label":"听力题面","source_breakdown":"题面1 / ASR1 / 合计2"}],"warnings":["contains_asr"]},"a8ad1a3191698ea4624e1304":{"word_id":"a8ad1a3191698ea4624e1304","display_form":"継続","lemma_form":"継続","reading":"けいぞく","pos_major":"名詞","pos_label":"名词","pos_bucket":"noun","group":"content","group_label":"实词","counts":{"all":2,"total":2,"solving":2,"listening_prompt":0,"listening_transcript":0,"listening_asr":0,"listening_heard":0,"listening_total":0},"paper_counts":{"all":2,"solving":2,"listening_prompt":0,"listening_heard":0,"listening_total":0},"first_year":2016,"last_year":2019,"years_present":["2016","2019"],"source_flags":["solving"],"has_asr":false,"quality_flags":[],"dict_query":"継続","dict_query_alt":["けいぞく"],"moji_url":"https://www.mojidict.com/searchText/%E7%B6%99%E7%B6%9A","surface_variant_count":1,"reading_variant_count":1,"sense_ambiguous":false,"variants_preview":[["継続",2]],"top_sources":[{"paper_id":"gaokao-ja-2016-national-standard","paper_label":"2016 全国卷","year":"2016","solving":1,"listening_prompt":0,"listening_transcript":0,"listening_asr":0,"total":1,"has_asr":false,"quality_flags":[],"source_label":"解题","source_breakdown":"解题1 / 合计1"},{"paper_id":"gaokao-ja-2019-national-standard","paper_label":"2019 全国卷","year":"2019","solving":1,"listening_prompt":0,"listening_transcript":0,"listening_asr":0,"total":1,"has_asr":false,"quality_flags":[],"source_label":"解题","source_breakdown":"解题1 / 合计1"}],"dictionary":{"source":"JMdict","headword":"継続","reading":"けいぞく","glosses":["continuation","continuance","maintenance","persistence"],"parts":["n","vs","vt"],"entry_id":"1251810"},"examples":[{"text":"…えた時は14分4秒。( ア )に対して、腹式呼吸は9分32秒と短った。実験を行った20分の間に3分以上継続する眠りまで到達したのは、羊を数えた場合の5人に対して、腹式呼吸は9人と約2倍だった。","paper_label":"2016 全国卷","paper_id":"gaokao-ja-2016-national-standard","year":"2016","source":"解题","has_asr":false}],"variant_counts":[["継続",2]],"year_distribution":{"2016":1,"2019":1},"paper_distribution":[{"paper_id":"gaokao-ja-2016-national-standard","paper_label":"2016 全国卷","year":"2016","solving":1,"listening_prompt":0,"listening_transcript":0,"listening_asr":0,"total":1,"has_asr":false,"quality_flags":[],"source_label":"解题","source_breakdown":"解题1 / 合计1"},{"paper_id":"gaokao-ja-2019-national-standard","paper_label":"2019 全国卷","year":"2019","solving":1,"listening_prompt":0,"listening_transcript":0,"listening_asr":0,"total":1,"has_asr":false,"quality_flags":[],"source_label":"解题","source_breakdown":"解题1 / 合计1"}],"warnings":[]},"a8a780f6fa44c58ecd74e7ec":{"word_id":"a8a780f6fa44c58ecd74e7ec","display_form":"部品","lemma_form":"部品","reading":"ぶひん","pos_major":"名詞","pos_label":"名词","pos_bucket":"noun","group":"content","group_label":"实词","counts":{"all":2,"total":2,"solving":0,"listening_prompt":1,"listening_transcript":0,"listening_asr":1,"listening_heard":1,"listening_total":2},"paper_counts":{"all":1,"solving":0,"listening_prompt":1,"listening_heard":1,"listening_total":1},"first_year":2013,"last_year":2013,"years_present":["2013"],"source_flags":["listening_prompt","listening_asr"],"has_asr":true,"quality_flags":[],"dict_query":"部品","dict_query_alt":["ぶひん"],"moji_url":"https://www.mojidict.com/searchText/%E9%83%A8%E5%93%81","surface_variant_count":1,"reading_variant_count":1,"sense_ambiguous":false,"variants_preview":[["部品",2]],"top_sources":[{"paper_id":"gaokao-ja-2013-national-standard","paper_label":"2013 全国卷","year":"2013","solving":0,"listening_prompt":1,"listening_transcript":0,"listening_asr":1,"total":2,"has_asr":true,"quality_flags":[],"source_label":"听力题面","source_breakdown":"题面1 / ASR1 / 合计2"}],"dictionary":{"source":"JMdict","headword":"部品","reading":"ぶひん","glosses":["parts","accessories","components"],"parts":["n"],"entry_id":"1499480"},"examples":[{"text":"A 大きい港 B 自動車工場 C 自動車の部品工場","paper_label":"2013 全国卷","paper_id":"gaokao-ja-2013-national-standard","year":"2013","source":"听力题面","has_asr":false},{"text":"昔は魚が美味しいことで大変有名でしたが、最近は近くの街に自動車工場とその部品の工場ができたため、魚より車で有名な港になりました。","paper_label":"2013 全国卷","paper_id":"gaokao-ja-2013-national-standard","year":"2013","source":"听力 ASR","has_asr":true}],"variant_counts":[["部品",2]],"year_distribution":{"2013":2},"paper_distribution":[{"paper_id":"gaokao-ja-2013-national-standard","paper_label":"2013 全国卷","year":"2013","solving":0,"listening_prompt":1,"listening_transcript":0,"listening_asr":1,"total":2,"has_asr":true,"quality_flags":[],"source_label":"听力题面","source_breakdown":"题面1 / ASR1 / 合计2"}],"warnings":["contains_asr"]},"a8a752cc81396c8e5f9f609f":{"word_id":"a8a752cc81396c8e5f9f609f","display_form":"あさい","lemma_form":"浅い","reading":"あさい","pos_major":"形容詞","pos_label":"形容词","pos_bucket":"adjective","group":"content","group_label":"实词","counts":{"all":1,"total":1,"solving":1,"listening_prompt":0,"listening_transcript":0,"listening_asr":0,"listening_heard":0,"listening_total":0},"paper_counts":{"all":1,"solving":1,"listening_prompt":0,"listening_heard":0,"listening_total":0},"first_year":2019,"last_year":2019,"years_present":["2019"],"source_flags":["solving"],"has_asr":false,"quality_flags":[],"dict_query":"浅い","dict_query_alt":["あさい"],"moji_url":"https://www.mojidict.com/searchText/%E6%B5%85%E3%81%84","surface_variant_count":1,"reading_variant_count":1,"sense_ambiguous":false,"variants_preview":[["あさい",1]],"top_sources":[{"paper_id":"gaokao-ja-2019-national-standard","paper_label":"2019 全国卷","year":"2019","solving":1,"listening_prompt":0,"listening_transcript":0,"listening_asr":0,"total":1,"has_asr":false,"quality_flags":[],"source_label":"解题","source_breakdown":"解题1 / 合计1"}],"dictionary":{"source":"JMdict","headword":"浅い","reading":"あさい","glosses":["shallow","superficial","slight (wound)","light (sleep)"],"parts":["adj-i"],"entry_id":"1390800"},"examples":[{"text":"A.あさい B.つらい C.おそい D.かるい","paper_label":"2019 全国卷","paper_id":"gaokao-ja-2019-national-standard","year":"2019","source":"解题","has_asr":false}],"variant_counts":[["あさい",1]],"year_distribution":{"2019":1},"paper_distribution":[{"paper_id":"gaokao-ja-2019-national-standard","paper_label":"2019 全国卷","year":"2019","solving":1,"listening_prompt":0,"listening_transcript":0,"listening_asr":0,"total":1,"has_asr":false,"quality_flags":[],"source_label":"解题","source_breakdown":"解题1 / 合计1"}],"warnings":["lookup_by_dictionary_form_recommended"]},"a851afcacd72c6a5944d441e":{"word_id":"a851afcacd72c6a5944d441e","display_form":"カ国","lemma_form":"箇国","reading":"かこく","pos_major":"名詞","pos_label":"名词","pos_bucket":"noun","group":"content","group_label":"实词","counts":{"all":1,"total":1,"solving":1,"listening_prompt":0,"listening_transcript":0,"listening_asr":0,"listening_heard":0,"listening_total":0},"paper_counts":{"all":1,"solving":1,"listening_prompt":0,"listening_heard":0,"listening_total":0},"first_year":2022,"last_year":2022,"years_present":["2022"],"source_flags":["solving"],"has_asr":false,"quality_flags":[],"dict_query":"箇国","dict_query_alt":["カ国","かこく"],"moji_url":"https://www.mojidict.com/searchText/%E7%AE%87%E5%9B%BD","surface_variant_count":1,"reading_variant_count":1,"sense_ambiguous":false,"variants_preview":[["カ国",1]],"top_sources":[{"paper_id":"gaokao-ja-2022-national-standard","paper_label":"2022 全国卷","year":"2022","solving":1,"listening_prompt":0,"listening_transcript":0,"listening_asr":0,"total":1,"has_asr":false,"quality_flags":[],"source_label":"解题","source_breakdown":"解题1 / 合计1"}],"dictionary":{"source":"JMdict","headword":"箇国","reading":"かこく","glosses":["counter for countries"],"parts":["ctr"],"entry_id":"2086750"},"examples":[{"text":"日本人は世界でも際立って睡眠時間が短い。2018年の調査では、経済力開発機構の加盟30カ国で最下位の7時間22分。米国の8時間48分に比べれば、確かに見劣りする。1960年には日本人も8時間1…","paper_label":"2022 全国卷","paper_id":"gaokao-ja-2022-national-standard","year":"2022","source":"解题","has_asr":false}],"variant_counts":[["カ国",1]],"year_distribution":{"2022":1},"paper_distribution":[{"paper_id":"gaokao-ja-2022-national-standard","paper_label":"2022 全国卷","year":"2022","solving":1,"listening_prompt":0,"listening_transcript":0,"listening_asr":0,"total":1,"has_asr":false,"quality_flags":[],"source_label":"解题","source_breakdown":"解题1 / 合计1"}],"warnings":["lookup_by_dictionary_form_recommended"]},"a82625dc06adcb8f68078674":{"word_id":"a82625dc06adcb8f68078674","display_form":"共同体","lemma_form":"共同体","reading":"きょうどうたい","pos_major":"名詞","pos_label":"名词","pos_bucket":"noun","group":"content","group_label":"实词","counts":{"all":1,"total":1,"solving":1,"listening_prompt":0,"listening_transcript":0,"listening_asr":0,"listening_heard":0,"listening_total":0},"paper_counts":{"all":1,"solving":1,"listening_prompt":0,"listening_heard":0,"listening_total":0},"first_year":2025,"last_year":2025,"years_present":["2025"],"source_flags":["solving"],"has_asr":false,"quality_flags":[],"dict_query":"共同体","dict_query_alt":["きょうどうたい"],"moji_url":"https://www.mojidict.com/searchText/%E5%85%B1%E5%90%8C%E4%BD%93","surface_variant_count":1,"reading_variant_count":1,"sense_ambiguous":false,"variants_preview":[["共同体",1]],"top_sources":[{"paper_id":"gaokao-ja-2025-national-standard","paper_label":"2025 全国卷","year":"2025","solving":1,"listening_prompt":0,"listening_transcript":0,"listening_asr":0,"total":1,"has_asr":false,"quality_flags":[],"source_label":"解题","source_breakdown":"解题1 / 合计1"}],"dictionary":{"source":"JMdict","headword":"共同体","reading":"きょうどうたい","glosses":["cooperative body","cooperative system","collective","community"],"parts":["n"],"entry_id":"1235040"},"examples":[{"text":"…のお年寄りたちは、おそらくどこかの地域の老人会の旅行という感じ。そのおばあちゃんは、若い頃からずっと「皆と同じ」を貫くことによって、地域共同体の中で、波風を立てずに暮らしてきたのだと思います。","paper_label":"2025 全国卷","paper_id":"gaokao-ja-2025-national-standard","year":"2025","source":"解题","has_asr":false}],"variant_counts":[["共同体",1]],"year_distribution":{"2025":1},"paper_distribution":[{"paper_id":"gaokao-ja-2025-national-standard","paper_label":"2025 全国卷","year":"2025","solving":1,"listening_prompt":0,"listening_transcript":0,"listening_asr":0,"total":1,"has_asr":false,"quality_flags":[],"source_label":"解题","source_breakdown":"解题1 / 合计1"}],"warnings":[]},"a80a592b6584057a6e5bf1a2":{"word_id":"a80a592b6584057a6e5bf1a2","display_form":"匂い","lemma_form":"匂い","reading":"におい","pos_major":"名詞","pos_label":"名词","pos_bucket":"noun","group":"content","group_label":"实词","counts":{"all":1,"total":1,"solving":1,"listening_prompt":0,"listening_transcript":0,"listening_asr":0,"listening_heard":0,"listening_total":0},"paper_counts":{"all":1,"solving":1,"listening_prompt":0,"listening_heard":0,"listening_total":0},"first_year":2001,"last_year":2001,"years_present":["2001"],"source_flags":["solving"],"has_asr":false,"quality_flags":[],"dict_query":"匂い","dict_query_alt":["におい"],"moji_url":"https://www.mojidict.com/searchText/%E5%8C%82%E3%81%84","surface_variant_count":1,"reading_variant_count":1,"sense_ambiguous":false,"variants_preview":[["匂い",1]],"top_sources":[{"paper_id":"gaokao-ja-2001-national-standard","paper_label":"2001 全国卷","year":"2001","solving":1,"listening_prompt":0,"listening_transcript":0,"listening_asr":0,"total":1,"has_asr":false,"quality_flags":[],"source_label":"解题","source_breakdown":"解题1 / 合计1"}],"dictionary":{"source":"JMdict","headword":"匂い","reading":"におい","glosses":["smell","scent","odour","odor"],"parts":["n"],"entry_id":"1599760"},"examples":[{"text":"この花、色がきれいですけど、( )匂いがしますから、買わないことにしましょう。","paper_label":"2001 全国卷","paper_id":"gaokao-ja-2001-national-standard","year":"2001","source":"解题","has_asr":false}],"variant_counts":[["匂い",1]],"year_distribution":{"2001":1},"paper_distribution":[{"paper_id":"gaokao-ja-2001-national-standard","paper_label":"2001 全国卷","year":"2001","solving":1,"listening_prompt":0,"listening_transcript":0,"listening_asr":0,"total":1,"has_asr":false,"quality_flags":[],"source_label":"解题","source_breakdown":"解题1 / 合计1"}],"warnings":[]},"a8f0f1620b75024613904dc8":{"word_id":"a8f0f1620b75024613904dc8","display_form":"厚い","lemma_form":"厚い","reading":"あつい","pos_major":"形容詞","pos_label":"形容词","pos_bucket":"adjective","group":"content","group_label":"实词","counts":{"all":1,"total":1,"solving":1,"listening_prompt":0,"listening_transcript":0,"listening_asr":0,"listening_heard":0,"listening_total":0},"paper_counts":{"all":1,"solving":1,"listening_prompt":0,"listening_heard":0,"listening_total":0},"first_year":2023,"last_year":2023,"years_present":["2023"],"source_flags":["solving"],"has_asr":false,"quality_flags":[],"dict_query":"厚い","dict_query_alt":["あつい"],"moji_url":"https://www.mojidict.com/searchText/%E5%8E%9A%E3%81%84","surface_variant_count":1,"reading_variant_count":1,"sense_ambiguous":false,"variants_preview":[["厚い",1]],"top_sources":[{"paper_id":"gaokao-ja-2023-national-standard","paper_label":"2023 全国卷","year":"2023","solving":1,"listening_prompt":0,"listening_transcript":0,"listening_asr":0,"total":1,"has_asr":false,"quality_flags":[],"source_label":"解题","source_breakdown":"解题1 / 合计1"}],"dictionary":{"source":"JMdict","headword":"厚い","reading":"あつい","glosses":["thick","deep","heavy","kind"],"parts":["adj-i"],"entry_id":"1275320"},"examples":[{"text":"教室から外を見ると、厚い雲が校庭に影を落としていた。亮介に何て言おうと考えしると、健太の心は、次第に沈みこんでいった。","paper_label":"2023 全国卷","paper_id":"gaokao-ja-2023-national-standard","year":"2023","source":"解题","has_asr":false}],"variant_counts":[["厚い",1]],"year_distribution":{"2023":1},"paper_distribution":[{"paper_id":"gaokao-ja-2023-national-standard","paper_label":"2023 全国卷","year":"2023","solving":1,"listening_prompt":0,"listening_transcript":0,"listening_asr":0,"total":1,"has_asr":false,"quality_flags":[],"source_label":"解题","source_breakdown":"解题1 / 合计1"}],"warnings":[]},"a8a5ef173c40698d503704ee":{"word_id":"a8a5ef173c40698d503704ee","display_form":"座談会","lemma_form":"座談会","reading":"ざだんかい","pos_major":"名詞","pos_label":"名词","pos_bucket":"noun","group":"content","group_label":"实词","counts":{"all":1,"total":1,"solving":1,"listening_prompt":0,"listening_transcript":0,"listening_asr":0,"listening_heard":0,"listening_total":0},"paper_counts":{"all":1,"solving":1,"listening_prompt":0,"listening_heard":0,"listening_total":0},"first_year":2000,"last_year":2000,"years_present":["2000"],"source_flags":["solving"],"has_asr":false,"quality_flags":[],"dict_query":"座談会","dict_query_alt":["ざだんかい"],"moji_url":"https://www.mojidict.com/searchText/%E5%BA%A7%E8%AB%87%E4%BC%9A","surface_variant_count":1,"reading_variant_count":1,"sense_ambiguous":false,"variants_preview":[["座談会",1]],"top_sources":[{"paper_id":"gaokao-ja-2000-national-standard","paper_label":"2000 全国卷","year":"2000","solving":1,"listening_prompt":0,"listening_transcript":0,"listening_asr":0,"total":1,"has_asr":false,"quality_flags":[],"source_label":"解题","source_breakdown":"解题1 / 合计1"}],"dictionary":{"source":"JMdict","headword":"座談会","reading":"ざだんかい","glosses":["symposium","round-table discussion"],"parts":["n"],"entry_id":"1291920"},"examples":[{"text":"大勢の留学生が座談会でいろいろ意見を交換していた。","paper_label":"2000 全国卷","paper_id":"gaokao-ja-2000-national-standard","year":"2000","source":"解题","has_asr":false}],"variant_counts":[["座談会",1]],"year_distribution":{"2000":1},"paper_distribution":[{"paper_id":"gaokao-ja-2000-national-standard","paper_label":"2000 全国卷","year":"2000","solving":1,"listening_prompt":0,"listening_transcript":0,"listening_asr":0,"total":1,"has_asr":false,"quality_flags":[],"source_label":"解题","source_breakdown":"解题1 / 合计1"}],"warnings":[]},"a8affa94897dc0a1d224b45a":{"word_id":"a8affa94897dc0a1d224b45a","display_form":"気の毒","lemma_form":"気の毒","reading":"きのどく","pos_major":"形状詞","pos_label":"形状詞","pos_bucket":"adjective","group":"other","group_label":"其他","counts":{"all":1,"total":1,"solving":0,"listening_prompt":0,"listening_transcript":0,"listening_asr":1,"listening_heard":1,"listening_total":1},"paper_counts":{"all":1,"solving":0,"listening_prompt":0,"listening_heard":1,"listening_total":1},"first_year":2018,"last_year":2018,"years_present":["2018"],"source_flags":["listening_asr"],"has_asr":true,"quality_flags":[],"dict_query":"気の毒","dict_query_alt":["きのどく"],"moji_url":"https://www.mojidict.com/searchText/%E6%B0%97%E3%81%AE%E6%AF%92","surface_variant_count":1,"reading_variant_count":1,"sense_ambiguous":false,"variants_preview":[["気の毒",1]],"top_sources":[{"paper_id":"gaokao-ja-2018-national-standard","paper_label":"2018 全国卷","year":"2018","solving":0,"listening_prompt":0,"listening_transcript":0,"listening_asr":1,"total":1,"has_asr":true,"quality_flags":[],"source_label":"听力 ASR","source_breakdown":"ASR1 / 合计1"}],"dictionary":{"source":"JMdict","headword":"気の毒","reading":"きのどく","glosses":["pitiful","unfortunate","poor","miserable"],"parts":["adj-na","n"],"entry_id":"1221770"},"examples":[],"variant_counts":[["気の毒",1]],"year_distribution":{"2018":1},"paper_distribution":[{"paper_id":"gaokao-ja-2018-national-standard","paper_label":"2018 全国卷","year":"2018","solving":0,"listening_prompt":0,"listening_transcript":0,"listening_asr":1,"total":1,"has_asr":true,"quality_flags":[],"source_label":"听力 ASR","source_breakdown":"ASR1 / 合计1"}],"warnings":["contains_asr"]}}
